pyvidesk/__init__.py
pyvidesk-0.0.1.dist-info/LICENSE
pyvidesk-0.0.1.dist-info/METADATA
pyvidesk-0.0.1.dist-info/WHEEL
pyvidesk-0.0.1.dist-info/top_level.txt
pyvidesk-0.0.1.dist-info/RECORD
