Metadata-Version: 2.1
Name: pyvidesk
Version: 0.0.1
Summary: Movidesk API client for Python
Home-page: https://github.com/vilanz/pyvidesk
Author: Vinicius Lanzarini
Author-email: vinicius.lanzarini@movidesk.com
License: UNKNOWN
Platform: UNKNOWN
Classifier: Programming Language :: Python :: 3
Classifier: License :: OSI Approved :: MIT License
Classifier: Operating System :: OS Independent
